Magics/Magics.py
Magics/__init__.py
Magics/__main__.py
Magics/macro.py
Magics/metgram.py
Magics/toolbox.py
Magics-1.0.7.dist-info/LICENSE
Magics-1.0.7.dist-info/METADATA
Magics-1.0.7.dist-info/WHEEL
Magics-1.0.7.dist-info/top_level.txt
Magics-1.0.7.dist-info/zip-safe
Magics-1.0.7.dist-info/RECORD
